MANIFEST.in
README.rst
setup.py
pycipher/__init__.py
pycipher/adfgvx.py
pycipher/adfgx.py
pycipher/affine.py
pycipher/atbash.py
pycipher/autokey.py
pycipher/base.py
pycipher/beaufort.py
pycipher/bifid.py
pycipher/caesar.py
pycipher/columnartransposition.py
pycipher/delastelle.py
pycipher/enigma.py
pycipher/foursquare.py
pycipher/fracmorse.py
pycipher/gronsfeld.py
pycipher/m209.py
pycipher/playfair.py
pycipher/polybius.py
pycipher/porta.py
pycipher/railfence.py
pycipher/rot13.py
pycipher/simplesubstitution.py
pycipher/util.py
pycipher/vigenere.py
pycipher.egg-info/PKG-INFO
pycipher.egg-info/SOURCES.txt
pycipher.egg-info/dependency_links.txt
pycipher.egg-info/top_level.txt
tests/__init__.py
tests/test_adfgvx.py
tests/test_adfgx.py
tests/test_affine.py
tests/test_atbash.py
tests/test_autokey.py
tests/test_beaufort.py
tests/test_bifid.py
tests/test_caesar.py
tests/test_coltrans.py
tests/test_enigma.py
tests/test_foursquare.py
tests/test_gronsfeld.py
tests/test_m209.py
tests/test_playfair.py
tests/test_polybius.py
tests/test_porta.py
tests/test_railfence.py
tests/test_rot13.py
tests/test_simple.py
tests/test_vigenere.py