Metadata-Version: 1.1
Name: pycipher
Version: 0.5.2
Summary: Several simple cipher algorithms
Home-page: https://github.com/jameslyons/pycipher
Author: James Lyons
Author-email: james.lyons0@gmail.com
License: UNKNOWN
Platform: UNKNOWN
Classifier: Development Status :: 3 - Alpha
Classifier: License :: OSI Approved :: MIT License
Classifier: Intended Audience :: Developers
Classifier: Operating System :: OS Independent
Classifier: Programming Language :: Python
